fastgraphml/__init__.py
fastgraphml/graph_embeddings/__init__.py
fastgraphml/graph_embeddings/utils.py
fastgraphml/graph_embeddings/downstream_tasks/__init__.py
fastgraphml/graph_embeddings/downstream_tasks/similarity_search.py
fastgraphml/graph_embeddings/downstream_tasks/visualization.py
fastgraphml/graph_embeddings/models/__init__.py
fastgraphml/graph_embeddings/models/dmgi.py
fastgraphml/graph_embeddings/models/gat.py
fastgraphml/graph_embeddings/models/graph_sage.py
fastgraphml/graph_embeddings/models/metapath2vec.py
fastgraphml-0.0.0.dist-info/METADATA
fastgraphml-0.0.0.dist-info/WHEEL
fastgraphml-0.0.0.dist-info/top_level.txt
fastgraphml-0.0.0.dist-info/RECORD
