Metadata-Version: 2.1
Name: fastgraphml
Version: 0.0.0
Summary: Given an input graph the library generates graph embeddings using Low-Code built on top of PyG
Home-page: https://github.com/arangoml/fastgraphml
Author: Sachin Sharma
Author-email: sachin@arangodb.com
License: MIT License
Keywords: arangodb,pyg,graph deep learning,graph embeddings,pytorch geometric,graph machine learning,graph neural networks
Platform: UNKNOWN
Classifier: Intended Audience :: Developers
Classifier: License :: OSI Approved :: MIT License
Classifier: Operating System :: OS Independent
Classifier: Programming Language :: Python :: 3
Classifier: Programming Language :: Python :: 3.8
Classifier: Programming Language :: Python :: 3.9
Classifier: Topic :: Utilities
Classifier: Typing :: Typed
Requires-Python: >=3.8
Requires-Dist: requests (==2.28.1)
Requires-Dist: sklearn (==0.0)
Requires-Dist: matplotlib (==3.5.2)
Requires-Dist: seaborn (==0.11.2)
Requires-Dist: matplotlib-inline (==0.1.2)
Requires-Dist: numpy (==1.22.4)
Requires-Dist: tqdm (==4.64.0)
Requires-Dist: umap-learn (==0.5.3)
Requires-Dist: adbpyg-adapter (==1.1.0)
Requires-Dist: python-arango (==7.4.1)
Requires-Dist: setuptools (==45)
Requires-Dist: arango-datasets (==1.0.0)
Provides-Extra: dev
Requires-Dist: black (==22.8.0) ; extra == 'dev'
Requires-Dist: pytest (==7.1.3) ; extra == 'dev'
Requires-Dist: sphinx (==5.1.1) ; extra == 'dev'
Requires-Dist: pre-commit (==2.20.0) ; extra == 'dev'
Requires-Dist: types-requests (==2.28.11.2) ; extra == 'dev'
Requires-Dist: flake8 (==5.0.4) ; extra == 'dev'
Requires-Dist: pytest-cov (==4.0.0) ; extra == 'dev'
Requires-Dist: isort (==5.10.1) ; extra == 'dev'
Requires-Dist: mypy (==0.982) ; extra == 'dev'
Requires-Dist: types-setuptools (==65.5.0.2) ; extra == 'dev'
Requires-Dist: bandit (==1.7.4) ; extra == 'dev'
